whereisthemouse/__init__.py
whereisthemouse-1.0.0.dist-info/METADATA
whereisthemouse-1.0.0.dist-info/WHEEL
whereisthemouse-1.0.0.dist-info/top_level.txt
whereisthemouse-1.0.0.dist-info/RECORD
