Metadata-Version: 2.1
Name: whereisthemouse
Version: 1.0.0
Summary: show mouse position and pixel value
Home-page: https://pypi.org/project/whereisthemouse/
Author: KuoYuanLi
Author-email: funny4875@gmail.com
Classifier: Programming Language :: Python :: 3
Classifier: License :: OSI Approved :: MIT License
Classifier: Operating System :: OS Independent
Requires-Python: >=3.6
Requires-Dist: pyautogui
Requires-Dist: keyboard
Requires-Dist: pyperclip
